Metadata-Version: 2.1
Name: italo-gbdist
Version: 0.2
Summary: Gaussian and Binomial distributions
Home-page: UNKNOWN
Author: Italo Castilho
License: UNKNOWN
Platform: UNKNOWN
